MANIFEST.in
VERSION
setup.py
canonical.ext.jose.egg-info/PKG-INFO
canonical.ext.jose.egg-info/SOURCES.txt
canonical.ext.jose.egg-info/dependency_links.txt
canonical.ext.jose.egg-info/requires.txt
canonical.ext.jose.egg-info/top_level.txt
canonical/ext/jose/__init__.py
canonical/ext/jose/package.json
canonical/ext/jose/utils.py
canonical/ext/jose/models/__init__.py
canonical/ext/jose/models/_joseheader.py
canonical/ext/jose/models/_jsonpublicwebkeyset.py
canonical/ext/jose/models/_jsonwebencryption.py
canonical/ext/jose/models/_jsonwebkey.py
canonical/ext/jose/models/_jsonwebkeybase.py
canonical/ext/jose/models/_jsonwebkeyedwardscurveprivate.py
canonical/ext/jose/models/_jsonwebkeyedwardscurvepublic.py
canonical/ext/jose/models/_jsonwebkeyellipticcurveprivate.py
canonical/ext/jose/models/_jsonwebkeyellipticcurvepublic.py
canonical/ext/jose/models/_jsonwebkeyinterface.py
canonical/ext/jose/models/_jsonwebkeyrsaprivate.py
canonical/ext/jose/models/_jsonwebkeyrsapublic.py
canonical/ext/jose/models/_jsonwebkeyset.py
canonical/ext/jose/models/_jsonwebkeysr25519private.py
canonical/ext/jose/models/_jsonwebkeysr25519public.py
canonical/ext/jose/models/_jsonwebsignature.py
canonical/ext/jose/models/_jsonwebtoken.py
canonical/ext/jose/models/_jwegeneralserialization.py
canonical/ext/jose/models/_jweheader.py
canonical/ext/jose/models/_jwsheader.py
canonical/ext/jose/models/_recipient.py
canonical/ext/jose/models/_signature.py
canonical/ext/jose/models/_signedjws.py
canonical/ext/jose/models/_symmetricencryptionkey.py
canonical/ext/jose/testing/compat.py
canonical/ext/jose/types/__init__.py
canonical/ext/jose/types/_contentencryptionalgorithm.py
canonical/ext/jose/types/_contentencryptionalgorithmconfig.py
canonical/ext/jose/types/_contentencryptionkey.py
canonical/ext/jose/types/_curvename.py
canonical/ext/jose/types/_encryptionresult.py
canonical/ext/jose/types/_jsonwebalgorithm.py
canonical/ext/jose/types/_jsonwebalgorithmconfig.py
canonical/ext/jose/types/_jwacontentencryptionalgorithm.py
canonical/ext/jose/types/_jwaencryptionalgorithm.py
canonical/ext/jose/types/_jwecompactencoded.py
canonical/ext/jose/types/_jwscompactencoded.py
